rootpath/__init__.py
rootpath/__init__.pyc
rootpath/append.py
rootpath/append.pyc
rootpath/detect.py
rootpath/detect.pyc
rootpath/tests/__init__.py
rootpath/tests/__main__.py
rootpath/tests/helper.py
rootpath/tests/test_append.py
rootpath/tests/test_detect.py
rootpath/utils/__init__.py
rootpath/utils/banner.py
rootpath-0.1.0.dist-info/METADATA
rootpath-0.1.0.dist-info/WHEEL
rootpath-0.1.0.dist-info/top_level.txt
rootpath-0.1.0.dist-info/zip-safe
rootpath-0.1.0.dist-info/RECORD
