Metadata-Version: 2.1
Name: rootpath
Version: 0.1.0
Summary: Python project/package root path detection.
Home-page: https://github.com/grimen/python-rootpath
Author: Jonas Grimfelt
Author-email: grimen@gmail.com
License: MIT
Download-URL: https://github.com/grimen/python-rootpath
Project-URL: repository, https://github.com/grimen/python-rootpath
Project-URL: bugs, https://github.com/grimen/python-rootpath/issues
Keywords: python,utlity,common,root,rootpath,root-path,detect,autodetect,auto-detect,project-root,project-root-path,package-root,package-root-path
Platform: UNKNOWN
Classifier: Topic :: Software Development :: Libraries
Classifier: Development Status :: 5 - Production/Stable
Classifier: Intended Audience :: Developers
Classifier: License :: OSI Approved :: MIT License
Classifier: Operating System :: POSIX
Classifier: Programming Language :: Python
Classifier: Programming Language :: Python :: 2
Classifier: Programming Language :: Python :: 2.7
Classifier: Programming Language :: Python :: 3
Classifier: Programming Language :: Python :: 3.6
Classifier: Programming Language :: Python :: 3.7
Classifier: Programming Language :: Python :: Implementation :: CPython
Classifier: Programming Language :: Python :: Implementation :: PyPy
